software_copyright_export_code/__init__.py
software_copyright_export_code-0.0.2.dist-info/LICENSE
software_copyright_export_code-0.0.2.dist-info/METADATA
software_copyright_export_code-0.0.2.dist-info/WHEEL
software_copyright_export_code-0.0.2.dist-info/top_level.txt
software_copyright_export_code-0.0.2.dist-info/RECORD
