Metadata-Version: 2.1
Name: software-copyright-export-code
Version: 0.0.2
Summary: Software copyright export code
Home-page: https://github.com/panhaoyu/software-copyright-export-code
Author: Haoyu Pan
Author-email: panhaoyu.china@outlook.com
License: UNKNOWN
Project-URL: Bug Tracker, https://github.com/panhaoyu/software-copyright-export-code/issues
Platform: UNKNOWN
Classifier: Programming Language :: Python :: 3
Classifier: License :: OSI Approved :: MIT License
Classifier: Operating System :: OS Independent
Requires-Python: >=3.8
